dbop_runner/__init__.py
dbop_runner/py.typed
dbop_runner/runner.py
dbop_runner-1.0.2.dist-info/licenses/LICENSE
dbop_runner-1.0.2.dist-info/METADATA
dbop_runner-1.0.2.dist-info/WHEEL
dbop_runner-1.0.2.dist-info/top_level.txt
dbop_runner-1.0.2.dist-info/RECORD
