Metadata-Version: 2.4
Name: dbop-runner
Version: 1.0.2
Summary: Resilient SQLAlchemy operation runner with retry, backoff, SAVEPOINTs, and per-operation timeouts.
Author: Youssef Khaya
License-Expression: MIT
Project-URL: Homepage, https://github.com/yokha/dbop-runner
Project-URL: Issues, https://github.com/yokha/dbop-runner/issues
Project-URL: Source, https://github.com/yokha/dbop-runner
Keywords: sqlalchemy,database,retry,backoff,transactions,savepoint,asyncio
Classifier: Programming Language :: Python :: 3
Classifier: Programming Language :: Python :: 3.9
Classifier: Programming Language :: Python :: 3.10
Classifier: Programming Language :: Python :: 3.11
Classifier: Programming Language :: Python :: 3.12
Classifier: Topic :: Database
Classifier: Topic :: Software Development :: Libraries
Requires-Python: >=3.9
License-File: LICENSE
Requires-Dist: SQLAlchemy<3,>=2.0
Provides-Extra: dev
Requires-Dist: ruff>=0.5.0; extra == "dev"
Requires-Dist: pytest>=8.0.0; extra == "dev"
Requires-Dist: pytest-xdist>=3.5.0; extra == "dev"
Requires-Dist: pytest-cov>=5.0.0; extra == "dev"
Requires-Dist: pytest-asyncio>=0.23.0; extra == "dev"
Requires-Dist: aiosqlite>=0.19.0; extra == "dev"
Requires-Dist: pre-commit>=3.7.0; extra == "dev"
Requires-Dist: build>=1.0; extra == "dev"
Requires-Dist: twine>=5.0; extra == "dev"
Provides-Extra: postgres
Requires-Dist: psycopg[binary]>=3.1.8; extra == "postgres"
Requires-Dist: asyncpg>=0.29.0; extra == "postgres"
Provides-Extra: mysql
Requires-Dist: pymysql>=1.1.0; extra == "mysql"
Requires-Dist: aiomysql>=0.2.0; extra == "mysql"
Dynamic: license-file
